nasim/__init__.py
nasim/demo.py
nasim/agents/__init__.py
nasim/agents/bruteforce_agent.py
nasim/agents/dqn_agent.py
nasim/agents/keyboard_agent.py
nasim/agents/ql_agent.py
nasim/agents/ql_replay_agent.py
nasim/agents/random_agent.py
nasim/envs/__init__.py
nasim/envs/action.py
nasim/envs/environment.py
nasim/envs/gym_env.py
nasim/envs/host_vector.py
nasim/envs/network.py
nasim/envs/observation.py
nasim/envs/render.py
nasim/envs/state.py
nasim/envs/utils.py
nasim/scenarios/__init__.py
nasim/scenarios/generator.py
nasim/scenarios/host.py
nasim/scenarios/loader.py
nasim/scenarios/scenario.py
nasim/scenarios/utils.py
nasim/scenarios/benchmark/__init__.py
nasim/scenarios/benchmark/generated.py
nasim/scenarios/benchmark/medium-multi-site.yaml
nasim/scenarios/benchmark/medium-single-site.yaml
nasim/scenarios/benchmark/medium.yaml
nasim/scenarios/benchmark/small-honeypot.yaml
nasim/scenarios/benchmark/small-linear.yaml
nasim/scenarios/benchmark/small.yaml
nasim/scenarios/benchmark/tiny-hard.yaml
nasim/scenarios/benchmark/tiny-small.yaml
nasim/scenarios/benchmark/tiny.yaml
nasim-0.12.0.dist-info/LICENSE.md
nasim-0.12.0.dist-info/METADATA
nasim-0.12.0.dist-info/WHEEL
nasim-0.12.0.dist-info/top_level.txt
nasim-0.12.0.dist-info/RECORD
