Metadata-Version: 2.1
Name: nasim
Version: 0.12.0
Summary: A simple and fast simulator for remote network pen-testing
Home-page: https://networkattacksimulator.readthedocs.io
Author: Jonathon Schwartz
Author-email: Jonathon.Schwartz@anu.edu.au
License: MIT
Project-URL: Documentation, https://networkattacksimulator.readthedocs.io
Project-URL: Source, https://github.com/Jjschwartz/NetworkAttackSimulator/
Platform: UNKNOWN
Classifier: Development Status :: 3 - Alpha
Classifier: License :: OSI Approved :: MIT License
Classifier: Programming Language :: Python :: 3
Classifier: Programming Language :: Python :: 3.8
Requires-Python: >=3.8
Provides-Extra: dqn
Provides-Extra: docs
Provides-Extra: test
Provides-Extra: all
License-File: LICENSE.md
